CHANGELOG.md
MANIFEST.in
README.md
README.rst
setup.py
kman/__init__.py
kman.egg-info/PKG-INFO
kman.egg-info/SOURCES.txt
kman.egg-info/dependency_links.txt
kman.egg-info/requires.txt
kman.egg-info/top_level.txt