Metadata-Version: 2.1
Name: kman
Version: 0.0.1
Summary: K-mer management tools
Home-page: https://github.com/ggirelli/kman
Author: Gabriele Girelli
Author-email: gabriele.girelli@scilifelab.se
License: MIT
Keywords: DNA kmer oligonucleotide oligomer unique count sequence sequencing
Platform: UNKNOWN
Classifier: Development Status :: 1 - Planning
Classifier: Intended Audience :: Science/Research
Classifier: Topic :: Scientific/Engineering :: Bio-Informatics
Classifier: License :: OSI Approved :: MIT License
Classifier: Programming Language :: Python :: 3 :: Only
